Zope2-4.0a6-py2.7-nspkg.pth
App/ApplicationManager.py
App/Common.py
App/Dialogs.py
App/Extensions.py
App/FactoryDispatcher.py
App/FindHomes.py
App/ImageFile.py
App/Management.py
App/ProductContext.py
App/Undo.py
App/ZApplication.py
App/__init__.py
App/bbb.py
App/class_init.py
App/config.py
App/interfaces.py
App/special_dtml.py
App/version_txt.py
App/dtml/cpContents.dtml
App/dtml/dbMain.dtml
App/dtml/manage.dtml
App/dtml/manage_form_title.dtml
App/dtml/manage_page_footer.dtml
App/dtml/manage_page_header.dtml
App/dtml/manage_page_style.css.dtml
App/dtml/manage_tabs.dtml
App/dtml/menu.dtml
App/dtml/undo.dtml
App/tests/__init__.py
App/tests/testImageFile.py
App/tests/testManagement.py
App/tests/test_ApplicationManager.py
App/tests/test_class_init.py
App/tests/test_setConfiguration.py
App/www/chooseDatabase.pt
App/www/zopelogo.png
OFS/Application.py
OFS/Cache.py
OFS/CopySupport.py
OFS/DTMLDocument.py
OFS/DTMLMethod.py
OFS/Document.py
OFS/EtagSupport.py
OFS/FindSupport.py
OFS/Folder.py
OFS/History.py
OFS/Image.py
OFS/LockItem.py
OFS/Lockable.py
OFS/Moniker.py
OFS/ObjectManager.py
OFS/OrderSupport.py
OFS/OrderedFolder.py
OFS/PropertyManager.py
OFS/PropertySheets.py
OFS/SimpleItem.py
OFS/Traversable.py
OFS/Uninstalled.py
OFS/__init__.py
OFS/absoluteurl.py
OFS/absoluteurl.zcml
OFS/bbb.py
OFS/configure.zcml
OFS/deprecated.zcml
OFS/event.py
OFS/event.txt
OFS/event.zcml
OFS/interfaces.py
OFS/meta.zcml
OFS/metaconfigure.py
OFS/metadirectives.py
OFS/misc_.py
OFS/owner.py
OFS/role.py
OFS/subscribers.py
OFS/userfolder.py
OFS/dtml/access.dtml
OFS/dtml/acquiredEdit.dtml
OFS/dtml/addOrderedFolder.dtml
OFS/dtml/addUser.dtml
OFS/dtml/brokenEdit.dtml
OFS/dtml/cacheNamespaceKeys.dtml
OFS/dtml/cacheable.dtml
OFS/dtml/cmassoc.dtml
OFS/dtml/documentAdd.dtml
OFS/dtml/documentEdit.dtml
OFS/dtml/documentProxy.dtml
OFS/dtml/editLocalRoles.dtml
OFS/dtml/editUser.dtml
OFS/dtml/editedDialog.dtml
Zope2-4.0a6.dist-info/DESCRIPTION.rst
Zope2-4.0a6.dist-info/METADATA
Zope2-4.0a6.dist-info/RECORD
Zope2-4.0a6.dist-info/WHEEL
Zope2-4.0a6.dist-info/entry_points.txt
Zope2-4.0a6.dist-info/metadata.json
Zope2-4.0a6.dist-info/namespace_packages.txt
Zope2-4.0a6.dist-info/top_level.txt
