Metadata-Version: 2.0
Name: Zope2
Version: 4.0a6
Summary: Zope2 application server / web framework
Home-page: https://zope.readthedocs.io/en/latest/
Author: Zope Foundation and Contributors
Author-email: zope-dev@zope.org
License: ZPL 2.1
Platform: UNKNOWN
Classifier: Development Status :: 6 - Mature
Classifier: Environment :: Web Environment
Classifier: Framework :: Zope2
Classifier: License :: OSI Approved :: Zope Public License
Classifier: Operating System :: OS Independent
Classifier: Programming Language :: Python
Classifier: Programming Language :: Python :: 2
Classifier: Programming Language :: Python :: 2.7
Classifier: Programming Language :: Python :: 3
Classifier: Programming Language :: Python :: 3.4
Classifier: Programming Language :: Python :: 3.5
Classifier: Programming Language :: Python :: 3.6
Classifier: Programming Language :: Python :: Implementation :: CPython
Requires-Dist: AccessControl (>=4.0a4)
Requires-Dist: Acquisition
Requires-Dist: BTrees
Requires-Dist: DateTime
Requires-Dist: DocumentTemplate
Requires-Dist: ExtensionClass
Requires-Dist: MultiMapping
Requires-Dist: PasteDeploy
Requires-Dist: Persistence
Requires-Dist: RestrictedPython
Requires-Dist: ZConfig (>=2.9.2)
Requires-Dist: ZODB
Requires-Dist: setuptools
Requires-Dist: six
Requires-Dist: transaction
Requires-Dist: waitress
Requires-Dist: zExceptions (>=3.4)
Requires-Dist: z3c.pt
Requires-Dist: zope.browser
Requires-Dist: zope.browsermenu
Requires-Dist: zope.browserpage (>=4.0)
Requires-Dist: zope.browserresource (>=3.11)
Requires-Dist: zope.component
Requires-Dist: zope.configuration
Requires-Dist: zope.container
Requires-Dist: zope.contentprovider
Requires-Dist: zope.contenttype
Requires-Dist: zope.deferredimport
Requires-Dist: zope.event
Requires-Dist: zope.exceptions
Requires-Dist: zope.globalrequest
Requires-Dist: zope.i18n[zcml]
Requires-Dist: zope.i18nmessageid
Requires-Dist: zope.interface (>=3.8)
Requires-Dist: zope.lifecycleevent
Requires-Dist: zope.location
Requires-Dist: zope.pagetemplate (>=4.0.2)
Requires-Dist: zope.processlifetime
Requires-Dist: zope.proxy
Requires-Dist: zope.ptresource
Requires-Dist: zope.publisher
Requires-Dist: zope.schema
Requires-Dist: zope.security
Requires-Dist: zope.sequencesort
Requires-Dist: zope.site
Requires-Dist: zope.size
Requires-Dist: zope.tal
Requires-Dist: zope.tales (>=3.5.0)
Requires-Dist: zope.testbrowser
Requires-Dist: zope.testing
Requires-Dist: zope.traversing
Requires-Dist: zope.viewlet
